rco_dl/__init__.py
rco_dl/__main__.py
rco_dl/rco_dl.py
rco_dl-1.3.dist-info/entry_points.txt
rco_dl-1.3.dist-info/WHEEL
rco_dl-1.3.dist-info/METADATA
rco_dl-1.3.dist-info/RECORD
