Metadata-Version: 2.1
Name: rco_dl
Version: 1.3
Summary: ReadComicOnline.to Downloader
Home-page: https://github.com/dyeray/readcomiconline-downloader/
License: UNKNOWN
Author: dyeray
Author-email: dyeray@gmail.com
Requires-Python: >=3
Requires-Dist: aiofiles==0.4.*
Requires-Dist: aiohttp==3.5.*
Requires-Dist: cfscrape
